setup.cfg
setup.py
Ivmjh.egg-info/PKG-INFO
Ivmjh.egg-info/SOURCES.txt
Ivmjh.egg-info/dependency_links.txt
Ivmjh.egg-info/top_level.txt
K/__init__.py
K/sa.py
K/tra.py