Metadata-Version: 2.1
Name: Ivmjh
Version: 0.1
Summary: Inventariado de un almacen
Home-page: https://github.com/davidguerrero04/repo
Author: DAVID LUENGAS
License: MIT
